surfaces_dashboard/Overview.py
surfaces_dashboard/__init__.py
surfaces_dashboard/page_setup.py
surfaces_dashboard/pages/1_1D_test_functions.py
surfaces_dashboard/pages/2_2D_test_functions.py
surfaces_dashboard/pages/3_ND_test_functions.py
surfaces_dashboard/pages/4_Machine_Learning_test_functions.py
surfaces_dashboard/pages/__init__.py
surfaces_dashboard/test_functions/__init__.py
surfaces_dashboard/test_functions/test_functions_1D.py
surfaces_dashboard/test_functions/test_functions_2D.py
surfaces_dashboard/test_functions/test_functions_ML.py
surfaces_dashboard/test_functions/test_functions_ND.py
surfaces_dashboard-0.0.2.dist-info/LICENSE
surfaces_dashboard-0.0.2.dist-info/METADATA
surfaces_dashboard-0.0.2.dist-info/WHEEL
surfaces_dashboard-0.0.2.dist-info/top_level.txt
surfaces_dashboard-0.0.2.dist-info/RECORD
